user/src/core/defines.v
`define INST_ADDR_BUS 31:0
`define INST_BUS 31:0
`define HOLD_FLAG_BUS 2:0
`define MEM_ADDR_BUS 31:0
`define MEM_BUS 31:0
`define REG_ADDR_BUS 4:0
`define REG_BUS 31:0
`define BYTE_BUS 7:0
`define FUNCT7_BUS 6:0
`define FUNCT3_BUS 2:0

//define the size of the memory and register file
`define REG_NUM 32
`define MEM_SIZE 128

`define RST 1'b1
`define RSTN 1'b0
`define WRITE_ENABLE 1'b1
`define WRITE_DISABLE 1'b0


`define JUMP_YES 1'b1
`define JUMP_NO 1'b0

`define ZERO_WORD 32'h0
`define ZERO_REG 5'b00000

`define HOLD_NONE 3'b000
`define HOLD_PC 3'b001
`define HOLD_IF 3'b010


`define INST_NOP 32'h00000013

//I type instructions
`define INST_TYPE_I 7'b0010011
`define INST_ADDI   3'b000
`define INST_SLTI   3'b010
`define INST_SLTIU  3'b011
`define INST_XORI   3'b100
`define INST_ORI    3'b110
`define INST_ANDI   3'b111
`define INST_SLLI   3'b001
`define INST_SRI    3'b101

// L type inst
`define INST_TYPE_L 7'b0000011
`define INST_LB     3'b000
`define INST_LH     3'b001
`define INST_LW     3'b010
`define INST_LBU    3'b100
`define INST_LHU    3'b101

// S type inst
`define INST_TYPE_S 7'b0100011
`define INST_SB     3'b000
`define INST_SH     3'b001
`define INST_SW     3'b010

// R type inst
`define INST_TYPE_R 7'b0110011
`define INST_ADD_SUB 3'b000
`define INST_SLL    3'b001
`define INST_SLT    3'b010
`define INST_SLTU   3'b011
`define INST_XOR    3'b100
`define INST_SR     3'b101
`define INST_OR     3'b110
`define INST_AND    3'b111

user/src/core/regs.v
`include "defines.v"

// 通用寄存器模块
module regs(

    input   wire                        clk                                         ,                   
    input   wire                        rst                                         ,                   

    // from ex
    input   wire                        we_i                                        ,           // 写寄存器标志
    input   wire    [`REG_ADDR_BUS]     waddr_i                                     ,           // 写寄存器地址
    input   wire    [`REG_BUS]          wdata_i                                     ,           // 写寄存器数据

    // from id
    input   wire    [`REG_ADDR_BUS]     raddr1_i                                    ,           // 读寄存器1地址

    // to id
    output  reg     [`REG_BUS]          rdata1_o                                    ,           // 读寄存器1数据

    // from id
    input   wire    [`REG_ADDR_BUS]     raddr2_i                                    ,           // 读寄存器2地址

    // to id
    output  reg     [`REG_BUS]          rdata2_o                                                // 读寄存器2数据

    );

    reg     [`REG_BUS]                  regs                        [0:`REG_NUM - 1];              
    

    // write regs
    always @ (posedge clk) begin
        if (rst == `RSTN) begin
            if ((we_i == `WRITE_ENABLE) && (waddr_i != `ZERO_REG)) begin
                regs[waddr_i] <= wdata_i;
            end
        end
    end

    // read reg1
    always @ (*) begin
        if (raddr1_i == `ZERO_REG) begin
            rdata1_o = `ZERO_WORD;
        // 如果读地址等于写地址，并且正在写操作，则直接返回写数据
        end else if (raddr1_i == waddr_i && we_i == `WRITE_ENABLE) begin
            rdata1_o = wdata_i;
        end else begin
            rdata1_o = regs[raddr1_i];
        end
    end

    // read reg2
    always @ (*) begin
        if (raddr2_i == `ZERO_REG) begin
            rdata2_o = `ZERO_WORD;
        // 如果读地址等于写地址，并且正在写操作，则直接返回写数据
        end else if (raddr2_i == waddr_i && we_i == `WRITE_ENABLE) begin
            rdata2_o = wdata_i;
        end else begin
            rdata2_o = regs[raddr2_i];
        end
    end
endmodule

user/src/core/id.v
`include "defines.v"

module id(
    input   wire                        rst                                         ,                   
    //from if_id
    input   wire    [`INST_ADDR_BUS]    inst_addr_i                                 ,                   
    input   wire    [`INST_BUS]         inst_i                                      ,                   

    //from regs
    input   wire    [`REG_BUS]          reg1_rdata_i                                 ,                   
    input   wire    [`REG_BUS]          reg2_rdata_i                                 ,                   

    //to regs
    output  reg     [`REG_ADDR_BUS]     reg1_raddr_o                                ,                   
    output  reg     [`REG_ADDR_BUS]     reg2_raddr_o                                ,                   
    

    //to ex
    output  reg     [`MEM_ADDR_BUS]     op1_o                                       ,                   
    output  reg     [`MEM_ADDR_BUS]     op2_o                                       ,                   
    output  reg                         reg_we_o                                    ,                   
    output  reg     [`REG_ADDR_BUS]     reg_waddr_o                                                     

);
    wire [`FUNCT7_BUS] opcode = inst_i[6:0];
    wire [`FUNCT3_BUS] funct3 = inst_i[14:12];
    wire [`FUNCT7_BUS] funct7 = inst_i[31:25];
    wire[`REG_ADDR_BUS] rd = inst_i[11:7];
    wire[`REG_ADDR_BUS] rs1 = inst_i[19:15];
    wire[`REG_ADDR_BUS] rs2 = inst_i[24:20];

    always @(*)begin
        reg1_raddr_o = rs1;
        reg2_raddr_o = rs2;
        op1_o = `ZERO_WORD;
        op2_o = `ZERO_WORD;

        case(opcode)
            `INST_TYPE_I:begin
                case(funct3)
                    `INST_ADDI, `INST_SLTI, `INST_SLTIU, `INST_XORI, `INST_ORI, `INST_ANDI, `INST_SLLI, `INST_SRI: begin
                        reg_we_o = `WRITE_ENABLE;
                        reg_waddr_o = rd;
                        reg1_raddr_o = rs1;
                        reg2_raddr_o = `ZERO_REG;
                        op1_o = reg1_rdata_i;
                        op2_o = {{20{inst_i[31]}}, inst_i[31:20]};
                    end
                    default: begin
                        reg_we_o = `WRITE_DISABLE;
                        reg_waddr_o = `ZERO_REG;
                        reg1_raddr_o = `ZERO_REG;
                        reg2_raddr_o = `ZERO_REG;
                    end
                endcase
            end
            `INST_TYPE_R:begin
                case(funct3)
                    `INST_ADD_SUB, `INST_SLL, `INST_SLT, `INST_SLTU, `INST_XOR, `INST_SR, `INST_OR, `INST_AND: begin
                            reg_we_o = `WRITE_DISABLE;
                            reg_waddr_o = rd;
                            reg1_raddr_o = rs1;
                            reg2_raddr_o = rs2;
                            op1_o = reg1_rdata_i;
                            op2_o = reg2_rdata_i;
                    end
                    default:begin
                        reg_we_o = `WRITE_DISABLE;
                        reg_waddr_o = `ZERO_REG;
                        reg1_raddr_o = `ZERO_REG;
                        reg2_raddr_o = `ZERO_REG;
                    end
                endcase
            end
            default:begin

            end
        endcase
    end
endmodule //decode

user/src/utils/gen_dff.v
`include "../core/defines.v"

module gen_pipe_dff #(
    parameter   DW                  =               32                          )(      

    input   wire                        clk                                         ,                   
    input   wire                        rst                                         ,                   
    input   wire                        hold_en                                     ,                   

    input   wire    [DW-1:0]            def_val                                     ,                   
    input   wire    [DW-1:0]            din                                         ,                   
    output  wire    [DW-1:0]            qout                                                            

    );

    reg     [DW-1:0]                    qout_r                                      ;                               

    always @ (posedge clk) begin
        if (rst == `RST | hold_en) begin
            qout_r <= def_val;
        end else begin
            qout_r <= din;
        end
    end

    assign qout = qout_r;

endmodule

user/src/core/if_id.v
`include "defines.v"
`include "../utils/gen_dff.v"

module if_id(
    input   wire                        clk                                         ,                   
    input   wire                        rst                                         ,                   

    input   wire    [`INST_BUS]         inst_i                                      ,           // 指令内容 
    input   wire    [`INST_ADDR_BUS]    inst_addr_i                                 ,           // 指令地址 

    input   wire    [`HOLD_FLAG_BUS]    hold_flag_i                                 ,           // 流水线暂停标志


    output  wire    [`INST_BUS]         inst_o                                      ,           // 指令内容 
    output  wire    [`INST_ADDR_BUS]    inst_addr_o                                             // 指令地址 

    );


    wire hold_en = (hold_flag_i >= `HOLD_IF);

    wire    [`INST_BUS]                 inst                                        ;                               
    gen_pipe_dff #(32) inst_ff(clk, rst, hold_en, `INST_NOP, inst_i, inst);
    assign inst_o = inst;

    wire    [`INST_ADDR_BUS]            inst_addr                                   ;                               
    gen_pipe_dff #(32) inst_addr_ff(clk, rst, hold_en, `ZERO_WORD, inst_addr_i, inst_addr);
    assign inst_addr_o = inst_addr;


endmodule

user/src/peripherals/rom.v
`include "../core/defines.v"

module rom(
    input   wire                        clk                                         ,                   
    input   wire                        rst                                         ,                   
    input   wire    [`MEM_ADDR_BUS]     addr_i                                      ,                   
    output  reg     [`INST_BUS]         inst_o                                                          
);
    reg     [`BYTE_BUS]                 _rom                        [`MEM_SIZE-1:0] ;                               
    reg     [7:0]                       i                                           ;                               
    initial begin
        $readmemh("/home/joknem/workspace/joknem_rv32/user/data/test.mem", _rom, 0, 127);
    end
    always @(*)begin
        if(rst == `RST)begin
            inst_o = `INST_NOP;
        end else begin
            inst_o = {{_rom[{addr_i[31:2], 2'b00}]},
                {_rom[{addr_i[31:2], 2'b01}]},
                {_rom[{addr_i[31:2], 2'b10}]}, 
                {_rom[{addr_i[31:2], 2'b11}]}};
        end
    end 
endmodule //rom

user/src/core/pc_reg.v
`include "defines.v"

module pc_reg(

    input   wire                        clk                                         ,                   
    input   wire                        rst                                         ,                   

    input   wire    [`MEM_ADDR_BUS]     start_i                                     ,           // 起始地址 
    input   wire                        jump_flag_i                                 ,           // 跳转标志 
    input   wire    [`INST_ADDR_BUS]    jump_addr_i                                 ,           // 跳转地址 
    input   wire    [`HOLD_FLAG_BUS]    hold_flag_i                                 ,           // 流水线暂停标志

    output  reg     [`INST_ADDR_BUS]    pc_o                                                    // PC指针 

    );


    always @ (posedge clk) begin
        if (rst == `RST) begin
            pc_o <= `ZERO_WORD;
        end else if (jump_flag_i == `JUMP_YES) begin
            pc_o <= jump_addr_i;
        end else if (hold_flag_i >= `HOLD_PC) begin
            pc_o <= pc_o;
        end else begin
            pc_o <= pc_o + 32'h4;
        end
    end

endmodule

user/sim/top.v
`timescale 1ns/1ns

`include "../src/core/defines.v"
`include "../src/core/pc_reg.v"
`include "../src/core/if_id.v"
`include "../src/utils/gen_dff.v"
`include "../src/peripherals/rom.v"
`include "../src/core/regs.v"
`include "../src/core/id.v"


module top();
    reg clk;
    reg rst;
    reg jump_flag_i;
    reg [`MEM_ADDR_BUS] start_i;
    reg [`MEM_ADDR_BUS] jump_addr_i;
    reg [`HOLD_FLAG_BUS] hold_flag_i;
    wire [`MEM_ADDR_BUS] pc_o;

    //rom module
    wire[`INST_BUS] rom_inst_o;

    //if_id module
    wire[`INST_BUS] ifid_inst_addr_o;
    wire[`INST_BUS] ifid_inst_o;

    //id module
    wire [`REG_ADDR_BUS] id_reg1_raddr_o;
    wire [`REG_ADDR_BUS] id_reg2_raddr_o;
    wire id_reg_we_o;
    wire [`MEM_ADDR_BUS] id_op1_o;
    wire [`MEM_ADDR_BUS] id_op2_o;
    wire [`REG_ADDR_BUS] id_reg_waddr_o;

    //regs module
    wire [`MEM_ADDR_BUS] regs_reg1_rdata_o;
    wire [`MEM_ADDR_BUS] regs_reg2_rdata_o;
    wire [`MEM_BUS] regs_op1_o;
    wire [`MEM_BUS] regs_op2_o;

    //FIXME: this is a test
    reg [`MEM_BUS] ex_wdata_o;

    always #10 clk = ~clk;


    initial begin:mem_init
        integer i;
        for (i = 0; i < 32; i = i + 1) begin
            regs_inst.regs[i] = `ZERO_WORD; // 初始化
            $display("x%-2d:0x%h", i, regs_inst.regs[i]);
        end
    end

    initial begin
        $dumpfile("./wave.vcd");
        $dumpvars(0, pc_reg_inst);
        $dumpvars(0, rom_inst);
        $dumpvars(0, if_id_inst);
        $dumpvars(0, id_inst);
        $dumpvars(0, regs_inst);
        clk = 0;
        rst = `RSTN;
        jump_flag_i = `JUMP_NO;
        jump_addr_i = `ZERO_WORD;
        hold_flag_i = `HOLD_NONE;
        start_i = `ZERO_WORD;
        #10 rst = `RST;
        #10 rst = `RSTN;
        #100 hold_flag_i = `HOLD_PC;
        #300 jump_flag_i = `JUMP_YES;
        jump_addr_i = 32'h00000004;
    end

    initial begin
        #2000;
        $display("Time Out.");
        $finish;
    end


    pc_reg pc_reg_inst(
        .clk(clk),
        .rst(rst),
        .start_i(start_i),
        .jump_flag_i(jump_flag_i),
        .jump_addr_i(jump_addr_i),
        .hold_flag_i(hold_flag_i),
        .pc_o(pc_o)
    );

    rom rom_inst(
        .clk(clk),
        .rst(rst),
        .addr_i(pc_o),
        .inst_o(rom_inst_o)
    );

    if_id if_id_inst(
        .clk(clk),
        .rst(rst),
        .hold_flag_i(hold_flag_i),
        .inst_i(rom_inst_o),
        .inst_addr_i(pc_o),
        .inst_addr_o(ifid_inst_addr_o),
        .inst_o(ifid_inst_o)
    );

    id id_inst(
        .rst(rst),
        .inst_i(ifid_inst_o),
        .inst_addr_i(ifid_inst_addr_o),
        .reg1_rdata_i(regs_reg1_rdata_o),
        .reg2_rdata_i(regs_reg1_rdata_o),
        .reg1_raddr_o(id_reg1_raddr_o),
        .reg2_raddr_o(id_reg2_raddr_o),
        .op1_o(id_op1_o),
        .op2_o(id_op2_o),
        .reg_we_o(id_we_o),
        .reg_waddr_o(id_reg_waddr_o)
    );

    regs regs_inst(
        .clk(clk),
        .rst(rst),
        //FIXME: this should from execute module not decode
        .raddr1_i(id_reg1_raddr_o),
        .raddr2_i(id_reg2_raddr_o),
        .we_i(id_we_o),
        .waddr_i(id_reg_waddr_o),
        .wdata_i(ex_wdata_o),
        .rdata1_o(regs_reg1_rdata_o),
        .rdata2_o(regs_reg2_rdata_o)
    );
endmodule //top

user/sim/wave.vcd
$date
	Mon May 20 02:07:11 2024
$end
$version
	Icarus Verilog
$end
$timescale
	1ns
$end
$scope module top $end
$scope module pc_reg_inst $end
$var wire 1 ! clk $end
$var wire 3 " hold_flag_i [2:0] $end
$var wire 32 # jump_addr_i [31:0] $end
$var wire 1 $ jump_flag_i $end
$var wire 1 % rst $end
$var wire 32 & start_i [31:0] $end
$var reg 32 ' pc_o [31:0] $end
$upscope $end
$upscope $end
$scope module top $end
$scope module rom_inst $end
$var wire 32 ( addr_i [31:0] $end
$var wire 1 ! clk $end
$var wire 1 % rst $end
$var reg 32 ) inst_o [31:0] $end
$upscope $end
$upscope $end
$scope module top $end
$scope module if_id_inst $end
$var wire 1 ! clk $end
$var wire 3 * hold_flag_i [2:0] $end
$var wire 32 + inst_addr_o [31:0] $end
$var wire 32 , inst_o [31:0] $end
$var wire 1 % rst $end
$var wire 32 - inst_i [31:0] $end
$var wire 32 . inst_addr_i [31:0] $end
$var wire 32 / inst_addr [31:0] $end
$var wire 32 0 inst [31:0] $end
$var wire 1 1 hold_en $end
$scope module inst_addr_ff $end
$var wire 1 ! clk $end
$var wire 32 2 def_val [31:0] $end
$var wire 1 1 hold_en $end
$var wire 1 % rst $end
$var wire 32 3 qout [31:0] $end
$var wire 32 4 din [31:0] $end
$var reg 32 5 qout_r [31:0] $end
$upscope $end
$scope module inst_ff $end
$var wire 1 ! clk $end
$var wire 32 6 def_val [31:0] $end
$var wire 1 1 hold_en $end
$var wire 1 % rst $end
$var wire 32 7 qout [31:0] $end
$var wire 32 8 din [31:0] $end
$var reg 32 9 qout_r [31:0] $end
$upscope $end
$upscope $end
$upscope $end
$scope module top $end
$scope module id_inst $end
$var wire 1 % rst $end
$var wire 5 : rs2 [4:0] $end
$var wire 5 ; rs1 [4:0] $end
$var wire 32 < reg2_rdata_i [31:0] $end
$var wire 32 = reg1_rdata_i [31:0] $end
$var wire 5 > rd [4:0] $end
$var wire 7 ? opcode [6:0] $end
$var wire 32 @ inst_i [31:0] $end
$var wire 32 A inst_addr_i [31:0] $end
$var wire 7 B funct7 [6:0] $end
$var wire 3 C funct3 [2:0] $end
$var reg 32 D op1_o [31:0] $end
$var reg 32 E op2_o [31:0] $end
$var reg 5 F reg1_raddr_o [4:0] $end
$var reg 5 G reg2_raddr_o [4:0] $end
$var reg 5 H reg_waddr_o [4:0] $end
$var reg 1 I reg_we_o $end
$upscope $end
$upscope $end
$scope module top $end
$scope module regs_inst $end
$var wire 1 ! clk $end
$var wire 5 J raddr1_i [4:0] $end
$var wire 5 K raddr2_i [4:0] $end
$var wire 1 % rst $end
$var wire 5 L waddr_i [4:0] $end
$var wire 32 M wdata_i [31:0] $end
$var wire 1 I we_i $end
$var reg 32 N rdata1_o [31:0] $end
$var reg 32 O rdata2_o [31:0] $end
$upscope $end
$upscope $end
$enddefinitions $end
#0
$dumpvars
bx O
bx N
bx M
bx L
bx K
bx J
xI
bx H
bx G
bx F
bx E
bx D
bx C
bx B
bx A
bx @
bx ?
bx >
bx =
bx <
bx ;
bx :
bx 9
bx 8
bx 7
b10011 6
bx 5
bx 4
bx 3
b0 2
01
bx 0
bx /
bx .
bx -
bx ,
bx +
b0 *
bx )
bx (
bx '
b0 &
0%
0$
b0 #
b0 "
0!
$end
#10
b0 O
b0 <
b0 =
b0 N
b0 H
b0 L
1I
b0 G
b0 K
b0 F
b0 J
b0 :
b0 ;
b0 >
b0 B
b0 C
b10011 ?
b0 E
b0 D
b0 '
b0 (
b0 .
b0 4
b10011 ,
b10011 @
b10011 0
b10011 7
b10011 9
b0 +
b0 A
b0 /
b0 3
b0 5
b10011 )
b10011 -
b10011 8
1%
1!
#20
b11111111000000010000000100010011 )
b11111111000000010000000100010011 -
b11111111000000010000000100010011 8
0%
0!
#30
bx D
bx <
bx =
bx N
b10 H
b10 L
b0 G
b0 K
b10 F
b10 J
b10000 :
b10 ;
b10 >
b1111111 B
b11111111111111111111111111110000 E
b100000010010011000100011 )
b100000010010011000100011 -
b100000010010011000100011 8
b11111111000000010000000100010011 ,
b11111111000000010000000100010011 @
b11111111000000010000000100010011 0
b11111111000000010000000100010011 7
b11111111000000010000000100010011 9
b100 '
b100 (
b100 .
b100 4
1!
#40
0!
#50
b1000000010000010000010011 )
b1000000010000010000010011 -
b1000000010000010000010011 8
b1000 :
b1100 >
b0 B
b10 C
b100011 ?
b0 E
b0 D
b1000 G
b1000 K
b1000 '
b1000 (
b1000 .
b1000 4
b100000010010011000100011 ,
b100000010010011000100011 @
b100000010010011000100011 0
b100000010010011000100011 7
b100000010010011000100011 9
b100 +
b100 A
b100 /
b100 3
b100 5
1!
#60
0!
#70
b10000 E
bx D
b1000 H
b1000 L
b0 G
b0 K
b10000 :
b1000 >
b0 C
b10011 ?
b100000000011110010011 )
b100000000011110010011 -
b100000000011110010011 8
b1000 +
b1000 A
b1000 /
b1000 3
b1000 5
b1000000010000010000010011 ,
b1000000010000010000010011 @
b1000000010000010000010011 0
b1000000010000010000010011 7
b1000000010000010000010011 9
b1100 '
b1100 (
b1100 .
b1100 4
1!
#80
0!
#90
b0 <
b0 =
b0 N
b1111 H
b1111 L
b0 F
b0 J
b1111000010100010011 )
b1111000010100010011 -
b1111000010100010011 8
b1 :
b0 ;
b1111 >
b1 E
b0 D
b0 G
b0 K
b10000 '
b10000 (
b10000 .
b10000 4
b100000000011110010011 ,
b100000000011110010011 @
b100000000011110010011 0
b100000000011110010011 7
b100000000011110010011 9
b1100 +
b1100 A
b1100 /
b1100 3
b1100 5
1!
#100
0!
#110
bx D
bx <
bx =
bx N
b1010 H
b1010 L
b1111 F
b1111 J
b0 :
b1111 ;
b1010 >
b0 E
b0 G
b0 K
b110000010010010000000011 )
b110000010010010000000011 -
b110000010010010000000011 8
b10000 +
b10000 A
b10000 /
b10000 3
b10000 5
b1111000010100010011 ,
b1111000010100010011 @
b1111000010100010011 0
b1111000010100010011 7
b1111000010100010011 9
b10100 '
b10100 (
b10100 .
b10100 4
1!
#120
0!
b1 "
b1 *
#130
b1100 G
b1100 K
b10 F
b10 J
b1100 :
b10 ;
b1000 >
b10 C
b11 ?
b0 E
b0 D
b110000010010010000000011 ,
b110000010010010000000011 @
b110000010010010000000011 0
b110000010010010000000011 7
b110000010010010000000011 9
b10100 +
b10100 A
b10100 /
b10100 3
b10100 5
1!
#140
0!
#150
1!
#160
0!
#170
1!
#180
0!
#190
1!
#200
0!
#210
1!
#220
0!
#230
1!
#240
0!
#250
1!
#260
0!
#270
1!
#280
0!
#290
1!
#300
0!
#310
1!
#320
0!
#330
1!
#340
0!
#350
1!
#360
0!
#370
1!
#380
0!
#390
1!
#400
0!
#410
1!
#420
0!
b100 #
1$
#430
b100000010010011000100011 )
b100000010010011000100011 -
b100000010010011000100011 8
b100 '
b100 (
b100 .
b100 4
1!
#440
0!
#450
bx O
b1000 G
b1000 K
b1000 :
b1100 >
b100011 ?
b100000010010011000100011 ,
b100000010010011000100011 @
b100000010010011000100011 0
b100000010010011000100011 7
b100000010010011000100011 9
b100 +
b100 A
b100 /
b100 3
b100 5
1!
